MANIFEST.in
NEWS.txt
README.rst
setup.py
src/wikidump/__init__.py
src/wikidump/analysis.py
src/wikidump/common.py
src/wikidump/config.py
src/wikidump/counter.py
src/wikidump/dataset.py
src/wikidump/doclength_threshold.py
src/wikidump/lang.py
src/wikidump/model.py
src/wikidump/paragraph.py
src/wikidump/parser.py
src/wikidump/regexps.py
src/wikidump/sampling.py
src/wikidump/segment.py
src/wikidump/utils.py
src/wikidump.egg-info/PKG-INFO
src/wikidump.egg-info/SOURCES.txt
src/wikidump.egg-info/dependency_links.txt
src/wikidump.egg-info/entry_points.txt
src/wikidump.egg-info/not-zip-safe
src/wikidump.egg-info/top_level.txt