Metadata-Version: 1.0
Name: wikidump
Version: 0.1.2
Summary: Tools to manipulate and extract data from wikipedia dumps
Home-page: http://github.com/saffsd/wikidump
Author: Marco Lui
Author-email: saffsd@gmail.com
License: GPL3
Keywords: wikipedia
Platform: UNKNOWN
Classifier: Development Status :: 3 - Alpha
Classifier: Environment :: Console
Classifier: Intended Audience :: Science/Research
Classifier: License :: OSI Approved :: GNU General Public License (GPL)
Classifier: Operating System :: OS Independent
Classifier: Programming Language :: Python
Classifier: Topic :: Scientific/Engineering :: Information Analysis
